cligame/__init__.py
cligame/game.py
cligame-0.2.2.dist-info/LICENSE
cligame-0.2.2.dist-info/METADATA
cligame-0.2.2.dist-info/WHEEL
cligame-0.2.2.dist-info/top_level.txt
cligame-0.2.2.dist-info/RECORD
