Metadata-Version: 2.1
Name: cligame
Version: 0.2.2
Summary: Python library to easily create CLI interactive games to learn or practice new concepts, without having to worry about the game related aspects such as score or timers
Home-page: https://github.com/Alex23rodriguez/cligame
Author: Alex Rodriguez
Author-email: alex.rodriguez.oro@gmail.com
Keywords: python,cli,game,interactive,cligame,terminal,learn
Classifier: Programming Language :: Python :: 3
Classifier: License :: OSI Approved :: GNU General Public License v3 (GPLv3)
Classifier: Operating System :: OS Independent
License-File: LICENSE
